odoo/addons/website_sale_suggest_create_account/README.rst
odoo/addons/website_sale_suggest_create_account/__init__.py
odoo/addons/website_sale_suggest_create_account/__manifest__.py
odoo/addons/website_sale_suggest_create_account/i18n/es.po
odoo/addons/website_sale_suggest_create_account/i18n/hr.po
odoo/addons/website_sale_suggest_create_account/i18n/it.po
odoo/addons/website_sale_suggest_create_account/i18n/sl.po
odoo/addons/website_sale_suggest_create_account/static/description/icon.png
odoo/addons/website_sale_suggest_create_account/views/website_sale.xml
odoo11_addon_website_sale_suggest_create_account-11.0.1.0.0.dist-info/DESCRIPTION.rst
odoo11_addon_website_sale_suggest_create_account-11.0.1.0.0.dist-info/METADATA
odoo11_addon_website_sale_suggest_create_account-11.0.1.0.0.dist-info/RECORD
odoo11_addon_website_sale_suggest_create_account-11.0.1.0.0.dist-info/WHEEL
odoo11_addon_website_sale_suggest_create_account-11.0.1.0.0.dist-info/metadata.json
odoo11_addon_website_sale_suggest_create_account-11.0.1.0.0.dist-info/top_level.txt
